README.md
setup.py
mpienv/__init__.py
mpienv/core.py
mpienv/mpi.py
mpienv/mpibase.py
mpienv/mpich.py
mpienv/mpienv_init.py
mpienv/mvapich.py
mpienv/ompi.py
mpienv/openmpi.py
mpienv/pip.py
mpienv/py.py
mpienv/util.py
mpienv.egg-info/PKG-INFO
mpienv.egg-info/SOURCES.txt
mpienv.egg-info/dependency_links.txt
mpienv.egg-info/entry_points.txt
mpienv.egg-info/top_level.txt
mpienv/command/__init__.py
mpienv/command/add.py
mpienv/command/autodiscover.py
mpienv/command/describe.py
mpienv/command/exec.py
mpienv/command/help.py
mpienv/command/info.py
mpienv/command/list.py
mpienv/command/prefix.py
mpienv/command/rename.py
mpienv/command/restore.py
mpienv/command/rm.py
mpienv/command/use.py