Metadata-Version: 1.0
Name: mpienv
Version: 0.2.0
Summary: MPI environment switcher
Home-page: https://github.com/keisukefukuda/mpienv
Author: Keisuke Fukuda
Author-email: keisukefukuda@gmail.com
License: UNKNOWN
Platform: UNKNOWN
